html_table_parser/__init__.py
html_table_parser/parser.py
html_table_parser_python3-0.1.5.dist-info/METADATA
html_table_parser_python3-0.1.5.dist-info/RECORD
html_table_parser_python3-0.1.5.dist-info/WHEEL
html_table_parser_python3-0.1.5.dist-info/top_level.txt
