Metadata-Version: 2.1
Name: html-table-parser-python3
Version: 0.1.5
Summary: A small and simple HTML table parser not requiring any external dependency.
Home-page: https://github.com/ahobsonsayers/html-table-parser-python3
Author: Arran Hobson Sayers
Author-email: ahobsonsayers@gmail.com
License: AGPLv3
Platform: UNKNOWN
Classifier: Programming Language :: Python :: 3 :: Only
Classifier: License :: OSI Approved :: GNU Affero General Public License v3
Classifier: Operating System :: OS Independent
Classifier: Topic :: Text Processing :: Markup :: HTML
